[
  {
    "full_name": "nateraw/stable-diffusion-videos",
    "stargazers_count": 2592,
    "open_issues_count": 43,
    "forks_count": 250
  },
  {
    "full_name": "starship/starship",
    "stargazers_count": 33868,
    "open_issues_count": 538,
    "forks_count": 1445
  },
  {
    "full_name": "microsoft/ML-For-Beginners",
    "stargazers_count": 47802,
    "open_issues_count": 11,
    "forks_count": 9763
  },
  {
    "full_name": "yunusozd/Speller",
    "stargazers_count": 2,
    "open_issues_count": 0,
    "forks_count": 0
  },
  {
    "full_name": "sairbarbaros/neurettes",
    "stargazers_count": 2,
    "open_issues_count": 0,
    "forks_count": 0
  },
  {
    "full_name": "papers-we-love/papers-we-love",
    "stargazers_count": 71594,
    "open_issues_count": 14,
    "forks_count": 5149
  },
  {
    "full_name": "avelino/awesome-go",
    "stargazers_count": 100365,
    "open_issues_count": 149,
    "forks_count": 10899
  },
  {
    "full_name": "golang/go",
    "stargazers_count": 110660,
    "open_issues_count": 8315,
    "forks_count": 16383
  },
  {
    "full_name": "ossu/computer-science",
    "stargazers_count": 138310,
    "open_issues_count": 17,
    "forks_count": 17875
  },
  {
    "full_name": "Asabeneh/30-Days-Of-JavaScript",
    "stargazers_count": 35253,
    "open_issues_count": 236,
    "forks_count": 8367
  },
  {
    "full_name": "git/git",
    "stargazers_count": 46009,
    "open_issues_count": 143,
    "forks_count": 24966
  },
  {
    "full_name": "charmbracelet/gum",
    "stargazers_count": 12960,
    "open_issues_count": 62,
    "forks_count": 246
  },
  {
    "full_name": "yunusozd/C-projeleri",
    "stargazers_count": 1,
    "open_issues_count": 1,
    "forks_count": 0
  },
  {
    "full_name": "vinta/awesome-python",
    "stargazers_count": 165500,
    "open_issues_count": 348,
    "forks_count": 23021
  },
  {
    "full_name": "sindresorhus/awesome",
    "stargazers_count": 250521,
    "open_issues_count": 59,
    "forks_count": 25445
  },
  {
    "full_name": "sdmg15/Best-websites-a-programmer-should-visit",
    "stargazers_count": 51239,
    "open_issues_count": 810,
    "forks_count": 6791
  },
  {
    "full_name": "nas5w/100-days-of-code-frontend",
    "stargazers_count": 2576,
    "open_issues_count": 4,
    "forks_count": 404
  },
  {
    "full_name": "xingyizhou/CenterNet",
    "stargazers_count": 6842,
    "open_issues_count": 434,
    "forks_count": 1911
  },
  {
    "full_name": "TheAlgorithms/Python",
    "stargazers_count": 157794,
    "open_issues_count": 156,
    "forks_count": 39862
  },
  {
    "full_name": "microsoft/WebTemplateStudio",
    "stargazers_count": 1987,
    "open_issues_count": 124,
    "forks_count": 207
  }
]