[
  {
    "full_name": "NVIDIA-AI-IOT/cuPCL",
    "stargazers_count": 349,
    "open_issues_count": 44,
    "forks_count": 68
  },
  {
    "full_name": "NVIDIA-AI-IOT/ros2_jetson",
    "stargazers_count": 73,
    "open_issues_count": 4,
    "forks_count": 21
  },
  {
    "full_name": "NVIDIA-ISAAC-ROS/isaac_ros_visual_slam",
    "stargazers_count": 493,
    "open_issues_count": 21,
    "forks_count": 81
  },
  {
    "full_name": "jvde-github/AIS-catcher-for-Android",
    "stargazers_count": 60,
    "open_issues_count": 2,
    "forks_count": 5
  },
  {
    "full_name": "dernasherbrezon/r2cloud",
    "stargazers_count": 228,
    "open_issues_count": 11,
    "forks_count": 31
  },
  {
    "full_name": "AlbertaSat/ex2_obc_software",
    "stargazers_count": 8,
    "open_issues_count": 6,
    "forks_count": 7
  },
  {
    "full_name": "daniestevez/gr-satellites",
    "stargazers_count": 675,
    "open_issues_count": 17,
    "forks_count": 145
  },
  {
    "full_name": "ArduSat/ArdusatSDK",
    "stargazers_count": 65,
    "open_issues_count": 3,
    "forks_count": 24
  },
  {
    "full_name": "Quetzal-1-CubeSat-Team/quetzal1-telemetry",
    "stargazers_count": 16,
    "open_issues_count": 0,
    "forks_count": 3
  },
  {
    "full_name": "Quetzal-1-CubeSat-Team/quetzal1-flight-software",
    "stargazers_count": 36,
    "open_issues_count": 0,
    "forks_count": 3
  },
  {
    "full_name": "nasa/nos3",
    "stargazers_count": 174,
    "open_issues_count": 42,
    "forks_count": 53
  },
  {
    "full_name": "abdulkadrtr/ROS2-FrontierBaseExplorationForAutonomousRobot",
    "stargazers_count": 4,
    "open_issues_count": 0,
    "forks_count": 3
  },
  {
    "full_name": "abdulkadrtr/mapMergeForMultiRobotMapping-ROS2",
    "stargazers_count": 2,
    "open_issues_count": 0,
    "forks_count": 0
  },
  {
    "full_name": "abdulkadrtr/ROS2-PurePursuitControl-PathPlanning-Tracking",
    "stargazers_count": 8,
    "open_issues_count": 0,
    "forks_count": 0
  },
  {
    "full_name": "nateraw/stable-diffusion-videos",
    "stargazers_count": 3361,
    "open_issues_count": 49,
    "forks_count": 306
  },
  {
    "full_name": "starship/starship",
    "stargazers_count": 35100,
    "open_issues_count": 560,
    "forks_count": 1502
  },
  {
    "full_name": "microsoft/ML-For-Beginners",
    "stargazers_count": 51104,
    "open_issues_count": 10,
    "forks_count": 10650
  },
  {
    "full_name": "yunusozd/Speller",
    "stargazers_count": 2,
    "open_issues_count": 0,
    "forks_count": 0
  },
  {
    "full_name": "sairbarbaros/neurettes",
    "stargazers_count": 2,
    "open_issues_count": 0,
    "forks_count": 0
  },
  {
    "full_name": "papers-we-love/papers-we-love",
    "stargazers_count": 74981,
    "open_issues_count": 7,
    "forks_count": 5594
  },
  {
    "full_name": "avelino/awesome-go",
    "stargazers_count": 104698,
    "open_issues_count": 151,
    "forks_count": 11088
  },
  {
    "full_name": "golang/go",
    "stargazers_count": 112767,
    "open_issues_count": 8496,
    "forks_count": 16829
  },
  {
    "full_name": "ossu/computer-science",
    "stargazers_count": 145823,
    "open_issues_count": 15,
    "forks_count": 18766
  },
  {
    "full_name": "Asabeneh/30-Days-Of-JavaScript",
    "stargazers_count": 37204,
    "open_issues_count": 283,
    "forks_count": 8817
  },
  {
    "full_name": "git/git",
    "stargazers_count": 46759,
    "open_issues_count": 146,
    "forks_count": 25283
  },
  {
    "full_name": "charmbracelet/gum",
    "stargazers_count": 13838,
    "open_issues_count": 74,
    "forks_count": 270
  },
  {
    "full_name": "yunusozd/C-projeleri",
    "stargazers_count": 1,
    "open_issues_count": 1,
    "forks_count": 0
  },
  {
    "full_name": "vinta/awesome-python",
    "stargazers_count": 173807,
    "open_issues_count": 368,
    "forks_count": 23520
  },
  {
    "full_name": "sindresorhus/awesome",
    "stargazers_count": 261621,
    "open_issues_count": 52,
    "forks_count": 26202
  },
  {
    "full_name": "sdmg15/Best-websites-a-programmer-should-visit",
    "stargazers_count": 51758,
    "open_issues_count": 809,
    "forks_count": 6861
  }
]