[
  {
    "full_name": "abdulkadrtr/ROS2-PurePursuitControl-PathPlanning-Tracking",
    "stargazers_count": 8,
    "open_issues_count": 0,
    "forks_count": 0
  },
  {
    "full_name": "nateraw/stable-diffusion-videos",
    "stargazers_count": 3327,
    "open_issues_count": 48,
    "forks_count": 303
  },
  {
    "full_name": "starship/starship",
    "stargazers_count": 34964,
    "open_issues_count": 563,
    "forks_count": 1489
  },
  {
    "full_name": "microsoft/ML-For-Beginners",
    "stargazers_count": 50462,
    "open_issues_count": 7,
    "forks_count": 10508
  },
  {
    "full_name": "yunusozd/Speller",
    "stargazers_count": 2,
    "open_issues_count": 0,
    "forks_count": 0
  },
  {
    "full_name": "sairbarbaros/neurettes",
    "stargazers_count": 2,
    "open_issues_count": 0,
    "forks_count": 0
  },
  {
    "full_name": "papers-we-love/papers-we-love",
    "stargazers_count": 74762,
    "open_issues_count": 7,
    "forks_count": 5574
  },
  {
    "full_name": "avelino/awesome-go",
    "stargazers_count": 104165,
    "open_issues_count": 148,
    "forks_count": 11064
  },
  {
    "full_name": "golang/go",
    "stargazers_count": 112548,
    "open_issues_count": 8457,
    "forks_count": 16799
  },
  {
    "full_name": "ossu/computer-science",
    "stargazers_count": 143468,
    "open_issues_count": 15,
    "forks_count": 18431
  },
  {
    "full_name": "Asabeneh/30-Days-Of-JavaScript",
    "stargazers_count": 36966,
    "open_issues_count": 268,
    "forks_count": 8743
  },
  {
    "full_name": "git/git",
    "stargazers_count": 46687,
    "open_issues_count": 148,
    "forks_count": 25254
  },
  {
    "full_name": "charmbracelet/gum",
    "stargazers_count": 13744,
    "open_issues_count": 66,
    "forks_count": 267
  },
  {
    "full_name": "yunusozd/C-projeleri",
    "stargazers_count": 1,
    "open_issues_count": 1,
    "forks_count": 0
  },
  {
    "full_name": "vinta/awesome-python",
    "stargazers_count": 172844,
    "open_issues_count": 360,
    "forks_count": 23470
  },
  {
    "full_name": "sindresorhus/awesome",
    "stargazers_count": 260526,
    "open_issues_count": 51,
    "forks_count": 26149
  },
  {
    "full_name": "sdmg15/Best-websites-a-programmer-should-visit",
    "stargazers_count": 51700,
    "open_issues_count": 809,
    "forks_count": 6858
  },
  {
    "full_name": "nas5w/100-days-of-code-frontend",
    "stargazers_count": 2589,
    "open_issues_count": 4,
    "forks_count": 416
  },
  {
    "full_name": "xingyizhou/CenterNet",
    "stargazers_count": 6905,
    "open_issues_count": 438,
    "forks_count": 1916
  },
  {
    "full_name": "TheAlgorithms/Python",
    "stargazers_count": 160513,
    "open_issues_count": 156,
    "forks_count": 40632
  },
  {
    "full_name": "microsoft/WebTemplateStudio",
    "stargazers_count": 1992,
    "open_issues_count": 131,
    "forks_count": 206
  }
]